cykooz/__init__.py
cykooz/heif/__init__.py
cykooz/heif/errors.py
cykooz/heif/image.py
cykooz/heif/pil.py
cykooz/heif/rust_lib.cpython-310-x86_64-linux-gnu.so
cykooz/heif/typing.py
cykooz.heif.libs/libde265-43d1073f.so
cykooz.heif.libs/libheif-7db04cbc.so.1.20.2
cykooz.heif.libs/libjpeg-e87d2658.so.62.2.0
cykooz.heif.libs/libmvec-2-583a17db.28.so
cykooz.heif.libs/libx265-968e821b.so.209
cykooz.heif-1.3.0.dist-info/METADATA
cykooz.heif-1.3.0.dist-info/WHEEL
cykooz.heif-1.3.0.dist-info/RECORD
cykooz.heif-1.3.0.dist-info/licenses/LICENSE
