Metadata-Version: 2.4
Name: cykooz.heif
Version: 1.3.0
Classifier: Development Status :: 5 - Production/Stable
Classifier: Programming Language :: Python
Classifier: Programming Language :: Python :: 3
Classifier: Programming Language :: Python :: 3.9
Classifier: Programming Language :: Python :: 3.10
Classifier: Programming Language :: Python :: 3.11
Classifier: Programming Language :: Python :: 3.12
Classifier: Programming Language :: Python :: 3.13
Classifier: Programming Language :: Python :: Implementation :: CPython
Classifier: Programming Language :: Rust
Classifier: Topic :: Multimedia :: Graphics
Classifier: Topic :: Multimedia :: Graphics :: Graphics Conversion
Classifier: License :: OSI Approved :: MIT License
Requires-Dist: wheel ; extra == 'dev'
Requires-Dist: maturin[zig] ; extra == 'dev'
Requires-Dist: maturin[zig,patchelf] ; platform_system == 'Linux' and extra == 'dev'
Requires-Dist: pytest ; extra == 'dev'
Requires-Dist: pillow ; extra == 'dev'
Requires-Dist: piexif ; extra == 'dev'
Provides-Extra: dev
License-File: LICENSE
Summary: A decoder of HEIF format of images
Keywords: heif,heic,libheif,pil,pillow
Home-Page: https://github.com/Cykooz/cykooz.heif
Requires-Python: >=3.9
